{
  "version": "8",
  "dialect": "postgres",
  "id": "a1670695-1153-4d3f-b76b-bdeea74b50fb",
  "prevIds": ["faf5114f-4005-4987-8000-5d9672851f5d"],
  "ddl": [
    {
      "values": ["active", "inactive"],
      "name": "business_vertical_status",
      "entityType": "enums",
      "schema": "public"
    },
    {
      "values": ["active", "inactive"],
      "name": "catalog_template_status",
      "entityType": "enums",
      "schema": "public"
    },
    {
      "values": ["active", "inactive", "suspended", "archived"],
      "name": "tenant_status",
      "entityType": "enums",
      "schema": "public"
    },
    {
      "isRlsEnabled": false,
      "name": "account",
      "entityType": "tables",
      "schema": "public"
    },
    {
      "isRlsEnabled": false,
      "name": "jwks",
      "entityType": "tables",
      "schema": "public"
    },
    {
      "isRlsEnabled": false,
      "name": "session",
      "entityType": "tables",
      "schema": "public"
    },
    {
      "isRlsEnabled": false,
      "name": "user",
      "entityType": "tables",
      "schema": "public"
    },
    {
      "isRlsEnabled": false,
      "name": "verification",
      "entityType": "tables",
      "schema": "public"
    },
    {
      "isRlsEnabled": false,
      "name": "business_verticals",
      "entityType": "tables",
      "schema": "public"
    },
    {
      "isRlsEnabled": false,
      "name": "catalog_templates",
      "entityType": "tables",
      "schema": "public"
    },
    {
      "isRlsEnabled": false,
      "name": "tenant_catalog_settings",
      "entityType": "tables",
      "schema": "public"
    },
    {
      "isRlsEnabled": false,
      "name": "tenants",
      "entityType": "tables",
      "schema": "public"
    },
    {
      "type": "text",
      "typeSchema": null,
      "notNull": true,
      "dimensions": 0,
      "default": null,
      "generated": null,
      "identity": null,
      "name": "id",
      "entityType": "columns",
      "schema": "public",
      "table": "account"
    },
    {
      "type": "text",
      "typeSchema": null,
      "notNull": true,
      "dimensions": 0,
      "default": null,
      "generated": null,
      "identity": null,
      "name": "account_id",
      "entityType": "columns",
      "schema": "public",
      "table": "account"
    },
    {
      "type": "text",
      "typeSchema": null,
      "notNull": true,
      "dimensions": 0,
      "default": null,
      "generated": null,
      "identity": null,
      "name": "provider_id",
      "entityType": "columns",
      "schema": "public",
      "table": "account"
    },
    {
      "type": "text",
      "typeSchema": null,
      "notNull": true,
      "dimensions": 0,
      "default": null,
      "generated": null,
      "identity": null,
      "name": "user_id",
      "entityType": "columns",
      "schema": "public",
      "table": "account"
    },
    {
      "type": "text",
      "typeSchema": null,
      "notNull": false,
      "dimensions": 0,
      "default": null,
      "generated": null,
      "identity": null,
      "name": "access_token",
      "entityType": "columns",
      "schema": "public",
      "table": "account"
    },
    {
      "type": "text",
      "typeSchema": null,
      "notNull": false,
      "dimensions": 0,
      "default": null,
      "generated": null,
      "identity": null,
      "name": "refresh_token",
      "entityType": "columns",
      "schema": "public",
      "table": "account"
    },
    {
      "type": "text",
      "typeSchema": null,
      "notNull": false,
      "dimensions": 0,
      "default": null,
      "generated": null,
      "identity": null,
      "name": "id_token",
      "entityType": "columns",
      "schema": "public",
      "table": "account"
    },
    {
      "type": "timestamp",
      "typeSchema": null,
      "notNull": false,
      "dimensions": 0,
      "default": null,
      "generated": null,
      "identity": null,
      "name": "access_token_expires_at",
      "entityType": "columns",
      "schema": "public",
      "table": "account"
    },
    {
      "type": "timestamp",
      "typeSchema": null,
      "notNull": false,
      "dimensions": 0,
      "default": null,
      "generated": null,
      "identity": null,
      "name": "refresh_token_expires_at",
      "entityType": "columns",
      "schema": "public",
      "table": "account"
    },
    {
      "type": "text",
      "typeSchema": null,
      "notNull": false,
      "dimensions": 0,
      "default": null,
      "generated": null,
      "identity": null,
      "name": "scope",
      "entityType": "columns",
      "schema": "public",
      "table": "account"
    },
    {
      "type": "text",
      "typeSchema": null,
      "notNull": false,
      "dimensions": 0,
      "default": null,
      "generated": null,
      "identity": null,
      "name": "password",
      "entityType": "columns",
      "schema": "public",
      "table": "account"
    },
    {
      "type": "timestamp",
      "typeSchema": null,
      "notNull": true,
      "dimensions": 0,
      "default": "now()",
      "generated": null,
      "identity": null,
      "name": "created_at",
      "entityType": "columns",
      "schema": "public",
      "table": "account"
    },
    {
      "type": "timestamp",
      "typeSchema": null,
      "notNull": true,
      "dimensions": 0,
      "default": null,
      "generated": null,
      "identity": null,
      "name": "updated_at",
      "entityType": "columns",
      "schema": "public",
      "table": "account"
    },
    {
      "type": "text",
      "typeSchema": null,
      "notNull": true,
      "dimensions": 0,
      "default": null,
      "generated": null,
      "identity": null,
      "name": "id",
      "entityType": "columns",
      "schema": "public",
      "table": "jwks"
    },
    {
      "type": "text",
      "typeSchema": null,
      "notNull": true,
      "dimensions": 0,
      "default": null,
      "generated": null,
      "identity": null,
      "name": "public_key",
      "entityType": "columns",
      "schema": "public",
      "table": "jwks"
    },
    {
      "type": "text",
      "typeSchema": null,
      "notNull": true,
      "dimensions": 0,
      "default": null,
      "generated": null,
      "identity": null,
      "name": "private_key",
      "entityType": "columns",
      "schema": "public",
      "table": "jwks"
    },
    {
      "type": "timestamp(6) with time zone",
      "typeSchema": null,
      "notNull": true,
      "dimensions": 0,
      "default": null,
      "generated": null,
      "identity": null,
      "name": "created_at",
      "entityType": "columns",
      "schema": "public",
      "table": "jwks"
    },
    {
      "type": "timestamp(6) with time zone",
      "typeSchema": null,
      "notNull": false,
      "dimensions": 0,
      "default": null,
      "generated": null,
      "identity": null,
      "name": "expires_at",
      "entityType": "columns",
      "schema": "public",
      "table": "jwks"
    },
    {
      "type": "text",
      "typeSchema": null,
      "notNull": true,
      "dimensions": 0,
      "default": null,
      "generated": null,
      "identity": null,
      "name": "id",
      "entityType": "columns",
      "schema": "public",
      "table": "session"
    },
    {
      "type": "timestamp",
      "typeSchema": null,
      "notNull": true,
      "dimensions": 0,
      "default": null,
      "generated": null,
      "identity": null,
      "name": "expires_at",
      "entityType": "columns",
      "schema": "public",
      "table": "session"
    },
    {
      "type": "text",
      "typeSchema": null,
      "notNull": true,
      "dimensions": 0,
      "default": null,
      "generated": null,
      "identity": null,
      "name": "token",
      "entityType": "columns",
      "schema": "public",
      "table": "session"
    },
    {
      "type": "timestamp",
      "typeSchema": null,
      "notNull": true,
      "dimensions": 0,
      "default": "now()",
      "generated": null,
      "identity": null,
      "name": "created_at",
      "entityType": "columns",
      "schema": "public",
      "table": "session"
    },
    {
      "type": "timestamp",
      "typeSchema": null,
      "notNull": true,
      "dimensions": 0,
      "default": null,
      "generated": null,
      "identity": null,
      "name": "updated_at",
      "entityType": "columns",
      "schema": "public",
      "table": "session"
    },
    {
      "type": "text",
      "typeSchema": null,
      "notNull": false,
      "dimensions": 0,
      "default": null,
      "generated": null,
      "identity": null,
      "name": "ip_address",
      "entityType": "columns",
      "schema": "public",
      "table": "session"
    },
    {
      "type": "text",
      "typeSchema": null,
      "notNull": false,
      "dimensions": 0,
      "default": null,
      "generated": null,
      "identity": null,
      "name": "user_agent",
      "entityType": "columns",
      "schema": "public",
      "table": "session"
    },
    {
      "type": "text",
      "typeSchema": null,
      "notNull": true,
      "dimensions": 0,
      "default": null,
      "generated": null,
      "identity": null,
      "name": "user_id",
      "entityType": "columns",
      "schema": "public",
      "table": "session"
    },
    {
      "type": "text",
      "typeSchema": null,
      "notNull": false,
      "dimensions": 0,
      "default": null,
      "generated": null,
      "identity": null,
      "name": "impersonated_by",
      "entityType": "columns",
      "schema": "public",
      "table": "session"
    },
    {
      "type": "text",
      "typeSchema": null,
      "notNull": true,
      "dimensions": 0,
      "default": null,
      "generated": null,
      "identity": null,
      "name": "id",
      "entityType": "columns",
      "schema": "public",
      "table": "user"
    },
    {
      "type": "text",
      "typeSchema": null,
      "notNull": true,
      "dimensions": 0,
      "default": null,
      "generated": null,
      "identity": null,
      "name": "name",
      "entityType": "columns",
      "schema": "public",
      "table": "user"
    },
    {
      "type": "text",
      "typeSchema": null,
      "notNull": true,
      "dimensions": 0,
      "default": null,
      "generated": null,
      "identity": null,
      "name": "email",
      "entityType": "columns",
      "schema": "public",
      "table": "user"
    },
    {
      "type": "boolean",
      "typeSchema": null,
      "notNull": true,
      "dimensions": 0,
      "default": "false",
      "generated": null,
      "identity": null,
      "name": "email_verified",
      "entityType": "columns",
      "schema": "public",
      "table": "user"
    },
    {
      "type": "text",
      "typeSchema": null,
      "notNull": false,
      "dimensions": 0,
      "default": null,
      "generated": null,
      "identity": null,
      "name": "image",
      "entityType": "columns",
      "schema": "public",
      "table": "user"
    },
    {
      "type": "timestamp",
      "typeSchema": null,
      "notNull": true,
      "dimensions": 0,
      "default": "now()",
      "generated": null,
      "identity": null,
      "name": "created_at",
      "entityType": "columns",
      "schema": "public",
      "table": "user"
    },
    {
      "type": "timestamp",
      "typeSchema": null,
      "notNull": true,
      "dimensions": 0,
      "default": "now()",
      "generated": null,
      "identity": null,
      "name": "updated_at",
      "entityType": "columns",
      "schema": "public",
      "table": "user"
    },
    {
      "type": "text",
      "typeSchema": null,
      "notNull": false,
      "dimensions": 0,
      "default": null,
      "generated": null,
      "identity": null,
      "name": "role",
      "entityType": "columns",
      "schema": "public",
      "table": "user"
    },
    {
      "type": "boolean",
      "typeSchema": null,
      "notNull": false,
      "dimensions": 0,
      "default": null,
      "generated": null,
      "identity": null,
      "name": "banned",
      "entityType": "columns",
      "schema": "public",
      "table": "user"
    },
    {
      "type": "text",
      "typeSchema": null,
      "notNull": false,
      "dimensions": 0,
      "default": null,
      "generated": null,
      "identity": null,
      "name": "ban_reason",
      "entityType": "columns",
      "schema": "public",
      "table": "user"
    },
    {
      "type": "timestamp(6) with time zone",
      "typeSchema": null,
      "notNull": false,
      "dimensions": 0,
      "default": null,
      "generated": null,
      "identity": null,
      "name": "ban_expires",
      "entityType": "columns",
      "schema": "public",
      "table": "user"
    },
    {
      "type": "text",
      "typeSchema": null,
      "notNull": true,
      "dimensions": 0,
      "default": null,
      "generated": null,
      "identity": null,
      "name": "id",
      "entityType": "columns",
      "schema": "public",
      "table": "verification"
    },
    {
      "type": "text",
      "typeSchema": null,
      "notNull": true,
      "dimensions": 0,
      "default": null,
      "generated": null,
      "identity": null,
      "name": "identifier",
      "entityType": "columns",
      "schema": "public",
      "table": "verification"
    },
    {
      "type": "text",
      "typeSchema": null,
      "notNull": true,
      "dimensions": 0,
      "default": null,
      "generated": null,
      "identity": null,
      "name": "value",
      "entityType": "columns",
      "schema": "public",
      "table": "verification"
    },
    {
      "type": "timestamp",
      "typeSchema": null,
      "notNull": true,
      "dimensions": 0,
      "default": null,
      "generated": null,
      "identity": null,
      "name": "expires_at",
      "entityType": "columns",
      "schema": "public",
      "table": "verification"
    },
    {
      "type": "timestamp",
      "typeSchema": null,
      "notNull": true,
      "dimensions": 0,
      "default": "now()",
      "generated": null,
      "identity": null,
      "name": "created_at",
      "entityType": "columns",
      "schema": "public",
      "table": "verification"
    },
    {
      "type": "timestamp",
      "typeSchema": null,
      "notNull": true,
      "dimensions": 0,
      "default": "now()",
      "generated": null,
      "identity": null,
      "name": "updated_at",
      "entityType": "columns",
      "schema": "public",
      "table": "verification"
    },
    {
      "type": "uuid",
      "typeSchema": null,
      "notNull": true,
      "dimensions": 0,
      "default": "gen_random_uuid()",
      "generated": null,
      "identity": null,
      "name": "id",
      "entityType": "columns",
      "schema": "public",
      "table": "business_verticals"
    },
    {
      "type": "text",
      "typeSchema": null,
      "notNull": true,
      "dimensions": 0,
      "default": null,
      "generated": null,
      "identity": null,
      "name": "code",
      "entityType": "columns",
      "schema": "public",
      "table": "business_verticals"
    },
    {
      "type": "text",
      "typeSchema": null,
      "notNull": true,
      "dimensions": 0,
      "default": null,
      "generated": null,
      "identity": null,
      "name": "name",
      "entityType": "columns",
      "schema": "public",
      "table": "business_verticals"
    },
    {
      "type": "text",
      "typeSchema": null,
      "notNull": false,
      "dimensions": 0,
      "default": null,
      "generated": null,
      "identity": null,
      "name": "description",
      "entityType": "columns",
      "schema": "public",
      "table": "business_verticals"
    },
    {
      "type": "business_vertical_status",
      "typeSchema": "public",
      "notNull": true,
      "dimensions": 0,
      "default": "'active'",
      "generated": null,
      "identity": null,
      "name": "status",
      "entityType": "columns",
      "schema": "public",
      "table": "business_verticals"
    },
    {
      "type": "timestamp with time zone",
      "typeSchema": null,
      "notNull": true,
      "dimensions": 0,
      "default": "now()",
      "generated": null,
      "identity": null,
      "name": "created_at",
      "entityType": "columns",
      "schema": "public",
      "table": "business_verticals"
    },
    {
      "type": "timestamp with time zone",
      "typeSchema": null,
      "notNull": true,
      "dimensions": 0,
      "default": "now()",
      "generated": null,
      "identity": null,
      "name": "updated_at",
      "entityType": "columns",
      "schema": "public",
      "table": "business_verticals"
    },
    {
      "type": "uuid",
      "typeSchema": null,
      "notNull": true,
      "dimensions": 0,
      "default": "gen_random_uuid()",
      "generated": null,
      "identity": null,
      "name": "id",
      "entityType": "columns",
      "schema": "public",
      "table": "catalog_templates"
    },
    {
      "type": "uuid",
      "typeSchema": null,
      "notNull": true,
      "dimensions": 0,
      "default": null,
      "generated": null,
      "identity": null,
      "name": "vertical_id",
      "entityType": "columns",
      "schema": "public",
      "table": "catalog_templates"
    },
    {
      "type": "text",
      "typeSchema": null,
      "notNull": true,
      "dimensions": 0,
      "default": null,
      "generated": null,
      "identity": null,
      "name": "name",
      "entityType": "columns",
      "schema": "public",
      "table": "catalog_templates"
    },
    {
      "type": "text",
      "typeSchema": null,
      "notNull": false,
      "dimensions": 0,
      "default": null,
      "generated": null,
      "identity": null,
      "name": "description",
      "entityType": "columns",
      "schema": "public",
      "table": "catalog_templates"
    },
    {
      "type": "integer",
      "typeSchema": null,
      "notNull": true,
      "dimensions": 0,
      "default": "1",
      "generated": null,
      "identity": null,
      "name": "version",
      "entityType": "columns",
      "schema": "public",
      "table": "catalog_templates"
    },
    {
      "type": "jsonb",
      "typeSchema": null,
      "notNull": true,
      "dimensions": 0,
      "default": "'[]'",
      "generated": null,
      "identity": null,
      "name": "default_categories_json",
      "entityType": "columns",
      "schema": "public",
      "table": "catalog_templates"
    },
    {
      "type": "jsonb",
      "typeSchema": null,
      "notNull": true,
      "dimensions": 0,
      "default": "'[]'",
      "generated": null,
      "identity": null,
      "name": "default_attributes_json",
      "entityType": "columns",
      "schema": "public",
      "table": "catalog_templates"
    },
    {
      "type": "jsonb",
      "typeSchema": null,
      "notNull": true,
      "dimensions": 0,
      "default": "'[]'",
      "generated": null,
      "identity": null,
      "name": "default_units_json",
      "entityType": "columns",
      "schema": "public",
      "table": "catalog_templates"
    },
    {
      "type": "jsonb",
      "typeSchema": null,
      "notNull": true,
      "dimensions": 0,
      "default": "'[]'",
      "generated": null,
      "identity": null,
      "name": "default_bot_flows_json",
      "entityType": "columns",
      "schema": "public",
      "table": "catalog_templates"
    },
    {
      "type": "jsonb",
      "typeSchema": null,
      "notNull": true,
      "dimensions": 0,
      "default": "'{}'",
      "generated": null,
      "identity": null,
      "name": "metadata_json",
      "entityType": "columns",
      "schema": "public",
      "table": "catalog_templates"
    },
    {
      "type": "boolean",
      "typeSchema": null,
      "notNull": true,
      "dimensions": 0,
      "default": "false",
      "generated": null,
      "identity": null,
      "name": "is_default",
      "entityType": "columns",
      "schema": "public",
      "table": "catalog_templates"
    },
    {
      "type": "catalog_template_status",
      "typeSchema": "public",
      "notNull": true,
      "dimensions": 0,
      "default": "'active'",
      "generated": null,
      "identity": null,
      "name": "status",
      "entityType": "columns",
      "schema": "public",
      "table": "catalog_templates"
    },
    {
      "type": "timestamp with time zone",
      "typeSchema": null,
      "notNull": true,
      "dimensions": 0,
      "default": "now()",
      "generated": null,
      "identity": null,
      "name": "created_at",
      "entityType": "columns",
      "schema": "public",
      "table": "catalog_templates"
    },
    {
      "type": "timestamp with time zone",
      "typeSchema": null,
      "notNull": true,
      "dimensions": 0,
      "default": "now()",
      "generated": null,
      "identity": null,
      "name": "updated_at",
      "entityType": "columns",
      "schema": "public",
      "table": "catalog_templates"
    },
    {
      "type": "uuid",
      "typeSchema": null,
      "notNull": true,
      "dimensions": 0,
      "default": null,
      "generated": null,
      "identity": null,
      "name": "tenant_id",
      "entityType": "columns",
      "schema": "public",
      "table": "tenant_catalog_settings"
    },
    {
      "type": "uuid",
      "typeSchema": null,
      "notNull": false,
      "dimensions": 0,
      "default": null,
      "generated": null,
      "identity": null,
      "name": "vertical_id",
      "entityType": "columns",
      "schema": "public",
      "table": "tenant_catalog_settings"
    },
    {
      "type": "uuid",
      "typeSchema": null,
      "notNull": false,
      "dimensions": 0,
      "default": null,
      "generated": null,
      "identity": null,
      "name": "catalog_template_id",
      "entityType": "columns",
      "schema": "public",
      "table": "tenant_catalog_settings"
    },
    {
      "type": "boolean",
      "typeSchema": null,
      "notNull": true,
      "dimensions": 0,
      "default": "true",
      "generated": null,
      "identity": null,
      "name": "require_sku",
      "entityType": "columns",
      "schema": "public",
      "table": "tenant_catalog_settings"
    },
    {
      "type": "boolean",
      "typeSchema": null,
      "notNull": true,
      "dimensions": 0,
      "default": "false",
      "generated": null,
      "identity": null,
      "name": "require_product_image",
      "entityType": "columns",
      "schema": "public",
      "table": "tenant_catalog_settings"
    },
    {
      "type": "boolean",
      "typeSchema": null,
      "notNull": true,
      "dimensions": 0,
      "default": "false",
      "generated": null,
      "identity": null,
      "name": "allow_backorders",
      "entityType": "columns",
      "schema": "public",
      "table": "tenant_catalog_settings"
    },
    {
      "type": "boolean",
      "typeSchema": null,
      "notNull": true,
      "dimensions": 0,
      "default": "false",
      "generated": null,
      "identity": null,
      "name": "enable_lots",
      "entityType": "columns",
      "schema": "public",
      "table": "tenant_catalog_settings"
    },
    {
      "type": "boolean",
      "typeSchema": null,
      "notNull": true,
      "dimensions": 0,
      "default": "false",
      "generated": null,
      "identity": null,
      "name": "enable_expiration_dates",
      "entityType": "columns",
      "schema": "public",
      "table": "tenant_catalog_settings"
    },
    {
      "type": "boolean",
      "typeSchema": null,
      "notNull": true,
      "dimensions": 0,
      "default": "false",
      "generated": null,
      "identity": null,
      "name": "enable_serial_numbers",
      "entityType": "columns",
      "schema": "public",
      "table": "tenant_catalog_settings"
    },
    {
      "type": "boolean",
      "typeSchema": null,
      "notNull": true,
      "dimensions": 0,
      "default": "false",
      "generated": null,
      "identity": null,
      "name": "enable_compatibility",
      "entityType": "columns",
      "schema": "public",
      "table": "tenant_catalog_settings"
    },
    {
      "type": "boolean",
      "typeSchema": null,
      "notNull": true,
      "dimensions": 0,
      "default": "false",
      "generated": null,
      "identity": null,
      "name": "enable_compliance_review",
      "entityType": "columns",
      "schema": "public",
      "table": "tenant_catalog_settings"
    },
    {
      "type": "integer",
      "typeSchema": null,
      "notNull": true,
      "dimensions": 0,
      "default": "15",
      "generated": null,
      "identity": null,
      "name": "default_reservation_ttl_minutes",
      "entityType": "columns",
      "schema": "public",
      "table": "tenant_catalog_settings"
    },
    {
      "type": "jsonb",
      "typeSchema": null,
      "notNull": true,
      "dimensions": 0,
      "default": "'{}'",
      "generated": null,
      "identity": null,
      "name": "rules_json",
      "entityType": "columns",
      "schema": "public",
      "table": "tenant_catalog_settings"
    },
    {
      "type": "timestamp with time zone",
      "typeSchema": null,
      "notNull": true,
      "dimensions": 0,
      "default": "now()",
      "generated": null,
      "identity": null,
      "name": "created_at",
      "entityType": "columns",
      "schema": "public",
      "table": "tenant_catalog_settings"
    },
    {
      "type": "timestamp with time zone",
      "typeSchema": null,
      "notNull": true,
      "dimensions": 0,
      "default": "now()",
      "generated": null,
      "identity": null,
      "name": "updated_at",
      "entityType": "columns",
      "schema": "public",
      "table": "tenant_catalog_settings"
    },
    {
      "type": "uuid",
      "typeSchema": null,
      "notNull": true,
      "dimensions": 0,
      "default": "gen_random_uuid()",
      "generated": null,
      "identity": null,
      "name": "id",
      "entityType": "columns",
      "schema": "public",
      "table": "tenants"
    },
    {
      "type": "text",
      "typeSchema": null,
      "notNull": true,
      "dimensions": 0,
      "default": null,
      "generated": null,
      "identity": null,
      "name": "name",
      "entityType": "columns",
      "schema": "public",
      "table": "tenants"
    },
    {
      "type": "text",
      "typeSchema": null,
      "notNull": true,
      "dimensions": 0,
      "default": null,
      "generated": null,
      "identity": null,
      "name": "slug",
      "entityType": "columns",
      "schema": "public",
      "table": "tenants"
    },
    {
      "type": "text",
      "typeSchema": null,
      "notNull": true,
      "dimensions": 0,
      "default": "'CO'",
      "generated": null,
      "identity": null,
      "name": "country",
      "entityType": "columns",
      "schema": "public",
      "table": "tenants"
    },
    {
      "type": "text",
      "typeSchema": null,
      "notNull": true,
      "dimensions": 0,
      "default": "'COP'",
      "generated": null,
      "identity": null,
      "name": "currency",
      "entityType": "columns",
      "schema": "public",
      "table": "tenants"
    },
    {
      "type": "text",
      "typeSchema": null,
      "notNull": true,
      "dimensions": 0,
      "default": "'America/Bogota'",
      "generated": null,
      "identity": null,
      "name": "timezone",
      "entityType": "columns",
      "schema": "public",
      "table": "tenants"
    },
    {
      "type": "tenant_status",
      "typeSchema": "public",
      "notNull": true,
      "dimensions": 0,
      "default": "'active'",
      "generated": null,
      "identity": null,
      "name": "status",
      "entityType": "columns",
      "schema": "public",
      "table": "tenants"
    },
    {
      "type": "timestamp with time zone",
      "typeSchema": null,
      "notNull": true,
      "dimensions": 0,
      "default": "now()",
      "generated": null,
      "identity": null,
      "name": "created_at",
      "entityType": "columns",
      "schema": "public",
      "table": "tenants"
    },
    {
      "type": "timestamp with time zone",
      "typeSchema": null,
      "notNull": true,
      "dimensions": 0,
      "default": "now()",
      "generated": null,
      "identity": null,
      "name": "updated_at",
      "entityType": "columns",
      "schema": "public",
      "table": "tenants"
    },
    {
      "type": "timestamp with time zone",
      "typeSchema": null,
      "notNull": false,
      "dimensions": 0,
      "default": null,
      "generated": null,
      "identity": null,
      "name": "deleted_at",
      "entityType": "columns",
      "schema": "public",
      "table": "tenants"
    },
    {
      "nameExplicit": true,
      "columns": [
        {
          "value": "user_id",
          "isExpression": false,
          "asc": true,
          "nullsFirst": false,
          "opclass": null
        }
      ],
      "isUnique": false,
      "where": null,
      "with": "",
      "method": "btree",
      "concurrently": false,
      "name": "account_user_id_idx",
      "entityType": "indexes",
      "schema": "public",
      "table": "account"
    },
    {
      "nameExplicit": true,
      "columns": [
        {
          "value": "user_id",
          "isExpression": false,
          "asc": true,
          "nullsFirst": false,
          "opclass": null
        }
      ],
      "isUnique": false,
      "where": null,
      "with": "",
      "method": "btree",
      "concurrently": false,
      "name": "session_user_id_idx",
      "entityType": "indexes",
      "schema": "public",
      "table": "session"
    },
    {
      "nameExplicit": true,
      "columns": [
        {
          "value": "identifier",
          "isExpression": false,
          "asc": true,
          "nullsFirst": false,
          "opclass": null
        }
      ],
      "isUnique": false,
      "where": null,
      "with": "",
      "method": "btree",
      "concurrently": false,
      "name": "verification_identifier_idx",
      "entityType": "indexes",
      "schema": "public",
      "table": "verification"
    },
    {
      "nameExplicit": true,
      "columns": [
        {
          "value": "code",
          "isExpression": false,
          "asc": true,
          "nullsFirst": false,
          "opclass": null
        }
      ],
      "isUnique": true,
      "where": null,
      "with": "",
      "method": "btree",
      "concurrently": false,
      "name": "business_verticals_code_idx",
      "entityType": "indexes",
      "schema": "public",
      "table": "business_verticals"
    },
    {
      "nameExplicit": true,
      "columns": [
        {
          "value": "status",
          "isExpression": false,
          "asc": true,
          "nullsFirst": false,
          "opclass": null
        }
      ],
      "isUnique": false,
      "where": null,
      "with": "",
      "method": "btree",
      "concurrently": false,
      "name": "business_verticals_status_idx",
      "entityType": "indexes",
      "schema": "public",
      "table": "business_verticals"
    },
    {
      "nameExplicit": true,
      "columns": [
        {
          "value": "vertical_id",
          "isExpression": false,
          "asc": true,
          "nullsFirst": false,
          "opclass": null
        }
      ],
      "isUnique": false,
      "where": null,
      "with": "",
      "method": "btree",
      "concurrently": false,
      "name": "catalog_templates_vertical_id_idx",
      "entityType": "indexes",
      "schema": "public",
      "table": "catalog_templates"
    },
    {
      "nameExplicit": true,
      "columns": [
        {
          "value": "vertical_id",
          "isExpression": false,
          "asc": true,
          "nullsFirst": false,
          "opclass": null
        },
        {
          "value": "is_default",
          "isExpression": false,
          "asc": true,
          "nullsFirst": false,
          "opclass": null
        }
      ],
      "isUnique": false,
      "where": null,
      "with": "",
      "method": "btree",
      "concurrently": false,
      "name": "catalog_templates_vertical_default_idx",
      "entityType": "indexes",
      "schema": "public",
      "table": "catalog_templates"
    },
    {
      "nameExplicit": true,
      "columns": [
        {
          "value": "vertical_id",
          "isExpression": false,
          "asc": true,
          "nullsFirst": false,
          "opclass": null
        },
        {
          "value": "name",
          "isExpression": false,
          "asc": true,
          "nullsFirst": false,
          "opclass": null
        },
        {
          "value": "version",
          "isExpression": false,
          "asc": true,
          "nullsFirst": false,
          "opclass": null
        }
      ],
      "isUnique": true,
      "where": null,
      "with": "",
      "method": "btree",
      "concurrently": false,
      "name": "catalog_templates_vertical_name_idx",
      "entityType": "indexes",
      "schema": "public",
      "table": "catalog_templates"
    },
    {
      "nameExplicit": true,
      "columns": [
        {
          "value": "vertical_id",
          "isExpression": false,
          "asc": true,
          "nullsFirst": false,
          "opclass": null
        }
      ],
      "isUnique": false,
      "where": null,
      "with": "",
      "method": "btree",
      "concurrently": false,
      "name": "tenant_catalog_settings_vertical_id_idx",
      "entityType": "indexes",
      "schema": "public",
      "table": "tenant_catalog_settings"
    },
    {
      "nameExplicit": true,
      "columns": [
        {
          "value": "catalog_template_id",
          "isExpression": false,
          "asc": true,
          "nullsFirst": false,
          "opclass": null
        }
      ],
      "isUnique": false,
      "where": null,
      "with": "",
      "method": "btree",
      "concurrently": false,
      "name": "tenant_catalog_settings_template_id_idx",
      "entityType": "indexes",
      "schema": "public",
      "table": "tenant_catalog_settings"
    },
    {
      "nameExplicit": true,
      "columns": [
        {
          "value": "slug",
          "isExpression": false,
          "asc": true,
          "nullsFirst": false,
          "opclass": null
        }
      ],
      "isUnique": true,
      "where": null,
      "with": "",
      "method": "btree",
      "concurrently": false,
      "name": "tenants_slug_idx",
      "entityType": "indexes",
      "schema": "public",
      "table": "tenants"
    },
    {
      "nameExplicit": true,
      "columns": [
        {
          "value": "status",
          "isExpression": false,
          "asc": true,
          "nullsFirst": false,
          "opclass": null
        }
      ],
      "isUnique": false,
      "where": null,
      "with": "",
      "method": "btree",
      "concurrently": false,
      "name": "tenants_status_idx",
      "entityType": "indexes",
      "schema": "public",
      "table": "tenants"
    },
    {
      "nameExplicit": false,
      "columns": ["user_id"],
      "schemaTo": "public",
      "tableTo": "user",
      "columnsTo": ["id"],
      "onUpdate": "NO ACTION",
      "onDelete": "CASCADE",
      "name": "account_user_id_user_id_fkey",
      "entityType": "fks",
      "schema": "public",
      "table": "account"
    },
    {
      "nameExplicit": false,
      "columns": ["user_id"],
      "schemaTo": "public",
      "tableTo": "user",
      "columnsTo": ["id"],
      "onUpdate": "NO ACTION",
      "onDelete": "CASCADE",
      "name": "session_user_id_user_id_fkey",
      "entityType": "fks",
      "schema": "public",
      "table": "session"
    },
    {
      "nameExplicit": false,
      "columns": ["vertical_id"],
      "schemaTo": "public",
      "tableTo": "business_verticals",
      "columnsTo": ["id"],
      "onUpdate": "CASCADE",
      "onDelete": "RESTRICT",
      "name": "catalog_templates_vertical_id_business_verticals_id_fkey",
      "entityType": "fks",
      "schema": "public",
      "table": "catalog_templates"
    },
    {
      "nameExplicit": false,
      "columns": ["tenant_id"],
      "schemaTo": "public",
      "tableTo": "tenants",
      "columnsTo": ["id"],
      "onUpdate": "CASCADE",
      "onDelete": "CASCADE",
      "name": "tenant_catalog_settings_tenant_id_tenants_id_fkey",
      "entityType": "fks",
      "schema": "public",
      "table": "tenant_catalog_settings"
    },
    {
      "nameExplicit": false,
      "columns": ["vertical_id"],
      "schemaTo": "public",
      "tableTo": "business_verticals",
      "columnsTo": ["id"],
      "onUpdate": "CASCADE",
      "onDelete": "RESTRICT",
      "name": "tenant_catalog_settings_vertical_id_business_verticals_id_fkey",
      "entityType": "fks",
      "schema": "public",
      "table": "tenant_catalog_settings"
    },
    {
      "nameExplicit": false,
      "columns": ["catalog_template_id"],
      "schemaTo": "public",
      "tableTo": "catalog_templates",
      "columnsTo": ["id"],
      "onUpdate": "CASCADE",
      "onDelete": "SET NULL",
      "name": "tenant_catalog_settings_vwdmxEGjQBkX_fkey",
      "entityType": "fks",
      "schema": "public",
      "table": "tenant_catalog_settings"
    },
    {
      "columns": ["id"],
      "nameExplicit": false,
      "name": "account_pkey",
      "schema": "public",
      "table": "account",
      "entityType": "pks"
    },
    {
      "columns": ["id"],
      "nameExplicit": false,
      "name": "jwks_pkey",
      "schema": "public",
      "table": "jwks",
      "entityType": "pks"
    },
    {
      "columns": ["id"],
      "nameExplicit": false,
      "name": "session_pkey",
      "schema": "public",
      "table": "session",
      "entityType": "pks"
    },
    {
      "columns": ["id"],
      "nameExplicit": false,
      "name": "user_pkey",
      "schema": "public",
      "table": "user",
      "entityType": "pks"
    },
    {
      "columns": ["id"],
      "nameExplicit": false,
      "name": "verification_pkey",
      "schema": "public",
      "table": "verification",
      "entityType": "pks"
    },
    {
      "columns": ["id"],
      "nameExplicit": false,
      "name": "business_verticals_pkey",
      "schema": "public",
      "table": "business_verticals",
      "entityType": "pks"
    },
    {
      "columns": ["id"],
      "nameExplicit": false,
      "name": "catalog_templates_pkey",
      "schema": "public",
      "table": "catalog_templates",
      "entityType": "pks"
    },
    {
      "columns": ["tenant_id"],
      "nameExplicit": false,
      "name": "tenant_catalog_settings_pkey",
      "schema": "public",
      "table": "tenant_catalog_settings",
      "entityType": "pks"
    },
    {
      "columns": ["id"],
      "nameExplicit": false,
      "name": "tenants_pkey",
      "schema": "public",
      "table": "tenants",
      "entityType": "pks"
    },
    {
      "nameExplicit": false,
      "columns": ["token"],
      "nullsNotDistinct": false,
      "name": "session_token_key",
      "schema": "public",
      "table": "session",
      "entityType": "uniques"
    },
    {
      "nameExplicit": false,
      "columns": ["email"],
      "nullsNotDistinct": false,
      "name": "user_email_key",
      "schema": "public",
      "table": "user",
      "entityType": "uniques"
    }
  ],
  "renames": []
}
